middleman_cli/__init__.py
middleman_cli/main.py
middleman_cli/commands/__init__.py
middleman_cli/commands/auth.py
middleman_cli/commands/config.py
middleman_cli/commands/jobs.py
middleman_cli/commands/run.py
middleman_cli/utils/__init__.py
middleman_cli/utils/api.py
middleman_cli-0.1.1.dist-info/METADATA
middleman_cli-0.1.1.dist-info/WHEEL
middleman_cli-0.1.1.dist-info/entry_points.txt
middleman_cli-0.1.1.dist-info/RECORD
